{"ProjectBreakpoints":"{\"Value\":{\"Gmail/ProcessGmails.xaml\":[{\"ConditionalExpression\":null,\"ActionExpression\":null,\"ExpectedHitCounter\":null,\"ShouldContinueAfterAction\":false,\"BreakpointType\":1,\"LocationIdentifier\":\"Login - Invoke Workflow File (Restaurent365\\\\\\\\Login.xaml)\",\"IsEnabled\":false,\"Annotation\":null,\"Id\":\"7a2f6b46-b5a1-457c-8164-eadacc6495a0\",\"ActivityIdRef\":\"InvokeWorkflowFile_8\",\"ActivityId\":\"1.2619\",\"ActivityName\":\"Login - Invoke Workflow File (Restaurent365\\\\\\\\Login.xaml)\",\"IsTransient\":false},{\"ConditionalExpression\":null,\"ActionExpression\":null,\"ExpectedHitCounter\":null,\"ShouldContinueAfterAction\":false,\"BreakpointType\":1,\"LocationIdentifier\":\"Extract Document Data\",\"IsEnabled\":false,\"Annotation\":null,\"Id\":\"ca510368-8984-4713-a2dd-847b8bb6954b\",\"ActivityIdRef\":\"ExtractDocumentDataWithDocumentData`1_4\",\"ActivityId\":\"1.2121\",\"ActivityName\":\"Extract Document Data\",\"IsTransient\":false},{\"ConditionalExpression\":null,\"ActionExpression\":null,\"ExpectedHitCounter\":null,\"ShouldContinueAfterAction\":false,\"BreakpointType\":1,\"LocationIdentifier\":\"Assign - check if Vendor name has any mathing vendor from list\",\"IsEnabled\":false,\"Annotation\":null,\"Id\":\"6dd29b9b-673c-4b3d-b889-09b8b311ddce\",\"ActivityIdRef\":\"Assign_11\",\"ActivityId\":\"1.2015\",\"ActivityName\":\"Assign - check if Vendor name has any mathing vendor from list\",\"IsTransient\":false},{\"ConditionalExpression\":null,\"ActionExpression\":null,\"ExpectedHitCounter\":null,\"ShouldContinueAfterAction\":false,\"BreakpointType\":1,\"LocationIdentifier\":\"Continue\",\"IsEnabled\":true,\"Annotation\":null,\"Id\":\"57891bf1-35aa-4c82-a52b-a268369e0424\",\"ActivityIdRef\":\"Continue_3\",\"ActivityId\":\"1.1932\",\"ActivityName\":\"Continue\",\"IsTransient\":false},{\"ConditionalExpression\":null,\"ActionExpression\":null,\"ExpectedHitCounter\":null,\"ShouldContinueAfterAction\":false,\"BreakpointType\":1,\"LocationIdentifier\":\"If GL date is more then 15 days after- skip invoice\",\"IsEnabled\":false,\"Annotation\":null,\"Id\":\"2bb76d9f-ff55-419b-9d30-6cef9dbea52b\",\"ActivityIdRef\":\"If_15\",\"ActivityId\":\"1.1903\",\"ActivityName\":\"If GL date is more then 15 days after- skip invoice\",\"IsTransient\":false},{\"ConditionalExpression\":null,\"ActionExpression\":null,\"ExpectedHitCounter\":null,\"ShouldContinueAfterAction\":false,\"BreakpointType\":1,\"LocationIdentifier\":\"Assign - currentShipLocation if null from BillingAddress\",\"IsEnabled\":false,\"Annotation\":null,\"Id\":\"8899149d-c5fd-4729-b6fe-f81479dccb2b\",\"ActivityIdRef\":\"Assign_26\",\"ActivityId\":\"1.1604\",\"ActivityName\":\"Assign - currentShipLocation if null from BillingAddress\",\"IsTransient\":false},{\"ConditionalExpression\":null,\"ActionExpression\":null,\"ExpectedHitCounter\":null,\"ShouldContinueAfterAction\":false,\"BreakpointType\":1,\"LocationIdentifier\":\"Else If JukeBoxy Music Vendor, extract locationf rom \\\"BillName\\\" field\",\"IsEnabled\":false,\"Annotation\":null,\"Id\":\"6acda769-dbd7-421f-bb70-24141d707b49\",\"ActivityIdRef\":\"IfElseIfV2_1\",\"ActivityId\":\"1.1063\",\"ActivityName\":\"Else If JukeBoxy Music Vendor, extract locationf rom \\\"BillName\\\" field\",\"IsTransient\":false},{\"ConditionalExpression\":null,\"ActionExpression\":null,\"ExpectedHitCounter\":null,\"ShouldContinueAfterAction\":false,\"BreakpointType\":1,\"LocationIdentifier\":\"Add Data Row - Report Success\",\"IsEnabled\":false,\"Annotation\":null,\"Id\":\"4f799297-9224-486f-999d-1c5dd3499366\",\"ActivityIdRef\":\"AddDataRow_4\",\"ActivityId\":\"1.649\",\"ActivityName\":\"Add Data Row - Report Success\",\"IsTransient\":false},{\"ConditionalExpression\":null,\"ActionExpression\":null,\"ExpectedHitCounter\":null,\"ShouldContinueAfterAction\":false,\"BreakpointType\":1,\"LocationIdentifier\":\"If Exception from Restaurent365, log to report\",\"IsEnabled\":false,\"Annotation\":null,\"Id\":\"a7046a46-4f2c-4f2f-bb4f-ee5fece55cc0\",\"ActivityIdRef\":\"If_4\",\"ActivityId\":\"1.585\",\"ActivityName\":\"If Exception from Restaurent365, log to report\",\"IsTransient\":false},{\"ConditionalExpression\":null,\"ActionExpression\":null,\"ExpectedHitCounter\":null,\"ShouldContinueAfterAction\":false,\"BreakpointType\":1,\"LocationIdentifier\":\"Add Data Row - Report Exception\",\"IsEnabled\":false,\"Annotation\":null,\"Id\":\"614e0037-a99e-4e04-a992-8c5dda445165\",\"ActivityIdRef\":\"AddDataRow_2\",\"ActivityId\":\"1.330\",\"ActivityName\":\"Add Data Row - Report Exception\",\"IsTransient\":false},{\"ConditionalExpression\":null,\"ActionExpression\":null,\"ExpectedHitCounter\":null,\"ShouldContinueAfterAction\":false,\"BreakpointType\":1,\"LocationIdentifier\":\"If location and vendor exists as per config, proceed\",\"IsEnabled\":false,\"Annotation\":null,\"Id\":\"31d15caf-7e26-43a3-b2eb-d83db3a6bedd\",\"ActivityIdRef\":\"If_3\",\"ActivityId\":\"1.242\",\"ActivityName\":\"If location and vendor exists as per config, proceed\",\"IsTransient\":false},{\"ConditionalExpression\":null,\"ActionExpression\":null,\"ExpectedHitCounter\":null,\"ShouldContinueAfterAction\":false,\"BreakpointType\":1,\"LocationIdentifier\":\"Log Message\",\"IsEnabled\":true,\"Annotation\":null,\"Id\":\"aa8233e3-3cf9-45d9-8065-db359d823ba1\",\"ActivityIdRef\":\"LogMessage_3\",\"ActivityId\":\"1.110\",\"ActivityName\":\"Log Message\",\"IsTransient\":false},{\"ConditionalExpression\":null,\"ActionExpression\":null,\"ExpectedHitCounter\":null,\"ShouldContinueAfterAction\":false,\"BreakpointType\":1,\"LocationIdentifier\":\"Try Catch - Main logic to process invoice\",\"IsEnabled\":false,\"Annotation\":null,\"Id\":\"5302f942-5f40-4cc0-952b-4dc52cf988e4\",\"ActivityIdRef\":\"TryCatch_1\",\"ActivityId\":\"1.85\",\"ActivityName\":\"Try Catch - Main logic to process invoice\",\"IsTransient\":false},{\"ConditionalExpression\":null,\"ActionExpression\":null,\"ExpectedHitCounter\":null,\"ShouldContinueAfterAction\":false,\"BreakpointType\":1,\"LocationIdentifier\":\"Write CSV - dump report data to csv report file\",\"IsEnabled\":false,\"Annotation\":null,\"Id\":\"6344e1fa-51e3-460a-856c-6f151cb7f9a7\",\"ActivityIdRef\":\"WriteCsvFile_1\",\"ActivityId\":\"1.7\",\"ActivityName\":\"Write CSV - dump report data to csv report file\",\"IsTransient\":false},{\"ConditionalExpression\":null,\"ActionExpression\":null,\"ExpectedHitCounter\":null,\"ShouldContinueAfterAction\":false,\"BreakpointType\":1,\"LocationIdentifier\":\"For Each Email of last day [Now -1 Day]\",\"IsEnabled\":false,\"Annotation\":null,\"Id\":\"a9ebec80-7ba4-49d5-847a-9de189f03463\",\"ActivityIdRef\":\"ForEachEmailConnections_1\",\"ActivityId\":\"1.5\",\"ActivityName\":\"For Each Email of last day [Now -1 Day]\",\"IsTransient\":false}],\"Restaurent365/ProcessInvoice.xaml\":[{\"ConditionalExpression\":null,\"ActionExpression\":null,\"ExpectedHitCounter\":null,\"ShouldContinueAfterAction\":false,\"BreakpointType\":1,\"LocationIdentifier\":\"Read LineItem Mappings Config\",\"IsEnabled\":false,\"Annotation\":null,\"Id\":\"b7ca3741-2a2f-4a95-b6ba-80eab0a48212\",\"ActivityIdRef\":\"ReadCsvFile_1\",\"ActivityId\":\"1.2065\",\"ActivityName\":\"Read LineItem Mappings Config\",\"IsTransient\":false},{\"ConditionalExpression\":null,\"ActionExpression\":null,\"ExpectedHitCounter\":null,\"ShouldContinueAfterAction\":false,\"BreakpointType\":1,\"LocationIdentifier\":\"Element Exists 'New Vendor'\",\"IsEnabled\":false,\"Annotation\":null,\"Id\":\"16e9db9d-5622-4616-b7b3-926356da54d3\",\"ActivityIdRef\":\"UiElementExists_4\",\"ActivityId\":\"1.1908\",\"ActivityName\":\"Element Exists 'New Vendor'\",\"IsTransient\":false},{\"ConditionalExpression\":null,\"ActionExpression\":null,\"ExpectedHitCounter\":null,\"ShouldContinueAfterAction\":false,\"BreakpointType\":1,\"LocationIdentifier\":\"Type Into 'Document Amount'\",\"IsEnabled\":false,\"Annotation\":null,\"Id\":\"5eda9be9-ada4-4b74-a762-c52b81ecd665\",\"ActivityIdRef\":\"NTypeInto_5\",\"ActivityId\":\"1.1723\",\"ActivityName\":\"Type Into 'Document Amount'\",\"IsTransient\":false},{\"ConditionalExpression\":null,\"ActionExpression\":null,\"ExpectedHitCounter\":null,\"ShouldContinueAfterAction\":false,\"BreakpointType\":1,\"LocationIdentifier\":\"If\",\"IsEnabled\":false,\"Annotation\":null,\"Id\":\"96444368-e468-4eba-812d-2559d2bfa543\",\"ActivityIdRef\":\"If_6\",\"ActivityId\":\"1.1659\",\"ActivityName\":\"If\",\"IsTransient\":false},{\"ConditionalExpression\":null,\"ActionExpression\":null,\"ExpectedHitCounter\":null,\"ShouldContinueAfterAction\":false,\"BreakpointType\":1,\"LocationIdentifier\":\"Else If\",\"IsEnabled\":false,\"Annotation\":null,\"Id\":\"cf56a1d9-bbae-422e-8b76-816d5687cb2b\",\"ActivityIdRef\":\"IfElseIfV2_2\",\"ActivityId\":\"1.1495\",\"ActivityName\":\"Else If\",\"IsTransient\":false},{\"ConditionalExpression\":null,\"ActionExpression\":null,\"ExpectedHitCounter\":null,\"ShouldContinueAfterAction\":false,\"BreakpointType\":1,\"LocationIdentifier\":\"Assign\",\"IsEnabled\":false,\"Annotation\":null,\"Id\":\"260642d1-9e00-4ab3-83c0-14dbe2d1ef9d\",\"ActivityIdRef\":\"Assign_12\",\"ActivityId\":\"1.1293\",\"ActivityName\":\"Assign\",\"IsTransient\":false},{\"ConditionalExpression\":null,\"ActionExpression\":null,\"ExpectedHitCounter\":null,\"ShouldContinueAfterAction\":false,\"BreakpointType\":1,\"LocationIdentifier\":\"Log Message\",\"IsEnabled\":false,\"Annotation\":null,\"Id\":\"a85fda32-eb70-4a14-a1ab-ff30f29117db\",\"ActivityIdRef\":\"LogMessage_16\",\"ActivityId\":\"1.1142\",\"ActivityName\":\"Log Message\",\"IsTransient\":false},{\"ConditionalExpression\":null,\"ActionExpression\":null,\"ExpectedHitCounter\":null,\"ShouldContinueAfterAction\":false,\"BreakpointType\":1,\"LocationIdentifier\":\"If\",\"IsEnabled\":false,\"Annotation\":null,\"Id\":\"010604b6-77e1-4a02-81fd-fb9117e133a3\",\"ActivityIdRef\":\"If_19\",\"ActivityId\":\"1.1117\",\"ActivityName\":\"If\",\"IsTransient\":false},{\"ConditionalExpression\":null,\"ActionExpression\":null,\"ExpectedHitCounter\":null,\"ShouldContinueAfterAction\":false,\"BreakpointType\":1,\"LocationIdentifier\":\"Click 'Clear'\",\"IsEnabled\":false,\"Annotation\":null,\"Id\":\"8e4a192a-4117-4848-bc91-d6d8ab2a1987\",\"ActivityIdRef\":\"NClick_24\",\"ActivityId\":\"1.1108\",\"ActivityName\":\"Click 'Clear'\",\"IsTransient\":false},{\"ConditionalExpression\":null,\"ActionExpression\":null,\"ExpectedHitCounter\":null,\"ShouldContinueAfterAction\":false,\"BreakpointType\":1,\"LocationIdentifier\":\"For Each currentItems\",\"IsEnabled\":false,\"Annotation\":null,\"Id\":\"d0bf6053-cb40-40a3-a20a-4ec6db5336d7\",\"ActivityIdRef\":\"ForEach`1_2\",\"ActivityId\":\"1.977\",\"ActivityName\":\"For Each currentItems\",\"IsTransient\":false},{\"ConditionalExpression\":null,\"ActionExpression\":null,\"ExpectedHitCounter\":null,\"ShouldContinueAfterAction\":false,\"BreakpointType\":1,\"LocationIdentifier\":\"Else If\",\"IsEnabled\":false,\"Annotation\":null,\"Id\":\"4fdf9482-6819-4973-b6ae-054732a65331\",\"ActivityIdRef\":\"IfElseIfV2_1\",\"ActivityId\":\"1.893\",\"ActivityName\":\"Else If\",\"IsTransient\":false},{\"ConditionalExpression\":null,\"ActionExpression\":null,\"ExpectedHitCounter\":null,\"ShouldContinueAfterAction\":false,\"BreakpointType\":1,\"LocationIdentifier\":\"If it is a \\\"Line item Invoice\\\", add Account differently\",\"IsEnabled\":false,\"Annotation\":null,\"Id\":\"2f61954f-1a3b-4bb5-acc5-6285d5794ce6\",\"ActivityIdRef\":\"If_10\",\"ActivityId\":\"1.552\",\"ActivityName\":\"If it is a \\\"Line item Invoice\\\", add Account differently\",\"IsTransient\":false},{\"ConditionalExpression\":null,\"ActionExpression\":null,\"ExpectedHitCounter\":null,\"ShouldContinueAfterAction\":false,\"BreakpointType\":1,\"LocationIdentifier\":\"Log Message - start adding lines\",\"IsEnabled\":false,\"Annotation\":null,\"Id\":\"b414a6e0-a2cf-4262-911d-8c3794f2b966\",\"ActivityIdRef\":\"LogMessage_2\",\"ActivityId\":\"1.450\",\"ActivityName\":\"Log Message - start adding lines\",\"IsTransient\":false},{\"ConditionalExpression\":null,\"ActionExpression\":null,\"ExpectedHitCounter\":null,\"ShouldContinueAfterAction\":false,\"BreakpointType\":1,\"LocationIdentifier\":\"Element Exists 'BUTTON'\",\"IsEnabled\":false,\"Annotation\":null,\"Id\":\"d4b04d59-0f4f-4263-84e8-46a8c26f9633\",\"ActivityIdRef\":\"UiElementExists_3\",\"ActivityId\":\"1.372\",\"ActivityName\":\"Element Exists 'BUTTON'\",\"IsTransient\":false},{\"ConditionalExpression\":null,\"ActionExpression\":null,\"ExpectedHitCounter\":null,\"ShouldContinueAfterAction\":false,\"BreakpointType\":1,\"LocationIdentifier\":\"If SplitUofM exists, update its value to restaurent line item\",\"IsEnabled\":false,\"Annotation\":null,\"Id\":\"3ae09f6e-fb2e-4976-a9e4-a22bfd5c361d\",\"ActivityIdRef\":\"If_11\",\"ActivityId\":\"1.270\",\"ActivityName\":\"If SplitUofM exists, update its value to restaurent line item\",\"IsTransient\":false},{\"ConditionalExpression\":null,\"ActionExpression\":null,\"ExpectedHitCounter\":null,\"ShouldContinueAfterAction\":false,\"BreakpointType\":1,\"LocationIdentifier\":\"If - \\\"Bypass lineitem if No Line Item Found for Invoice or Vendor exists in bypass vendor list\",\"IsEnabled\":false,\"Annotation\":null,\"Id\":\"1bfc8908-e8af-4e4a-9f1f-236e442b021c\",\"ActivityIdRef\":\"If_1\",\"ActivityId\":\"1.131\",\"ActivityName\":\"If - \\\"Bypass lineitem if No Line Item Found for Invoice or Vendor exists in bypass vendor list\",\"IsTransient\":false},{\"ConditionalExpression\":null,\"ActionExpression\":null,\"ExpectedHitCounter\":null,\"ShouldContinueAfterAction\":false,\"BreakpointType\":1,\"LocationIdentifier\":\"If R365 Process differently\",\"IsEnabled\":false,\"Annotation\":null,\"Id\":\"ec759451-a925-4e11-910a-3b7a45ad80a4\",\"ActivityIdRef\":\"If_15\",\"ActivityId\":\"1.110\",\"ActivityName\":\"If R365 Process differently\",\"IsTransient\":false},{\"ConditionalExpression\":null,\"ActionExpression\":null,\"ExpectedHitCounter\":null,\"ShouldContinueAfterAction\":false,\"BreakpointType\":1,\"LocationIdentifier\":\"Sequence - Add Invoice Line items\",\"IsEnabled\":false,\"Annotation\":null,\"Id\":\"47aae2ab-0a19-44cf-97df-5283a7b75102\",\"ActivityIdRef\":\"Sequence_43\",\"ActivityId\":\"1.109\",\"ActivityName\":\"Sequence - Add Invoice Line items\",\"IsTransient\":false},{\"ConditionalExpression\":null,\"ActionExpression\":null,\"ExpectedHitCounter\":null,\"ShouldContinueAfterAction\":false,\"BreakpointType\":1,\"LocationIdentifier\":\"Log Message\",\"IsEnabled\":false,\"Annotation\":null,\"Id\":\"53f937de-6945-467c-a3a6-1afbd0482d93\",\"ActivityIdRef\":\"LogMessage_7\",\"ActivityId\":\"1.89\",\"ActivityName\":\"Log Message\",\"IsTransient\":false},{\"ConditionalExpression\":null,\"ActionExpression\":null,\"ExpectedHitCounter\":null,\"ShouldContinueAfterAction\":false,\"BreakpointType\":1,\"LocationIdentifier\":\"Sequence\",\"IsEnabled\":false,\"Annotation\":null,\"Id\":\"22412678-7943-45a2-a16e-3f49f8d871c3\",\"ActivityIdRef\":\"Sequence_49\",\"ActivityId\":\"1.4\",\"ActivityName\":\"Sequence\",\"IsTransient\":false}],\"TestExtraction/TextExtractionData.xaml\":[{\"ConditionalExpression\":null,\"ActionExpression\":null,\"ExpectedHitCounter\":null,\"ShouldContinueAfterAction\":false,\"BreakpointType\":1,\"LocationIdentifier\":\"Log Message\",\"IsEnabled\":true,\"Annotation\":null,\"Id\":\"ffb3e3d7-1529-4933-9cb1-76a1b4333779\",\"ActivityIdRef\":\"LogMessage_1\",\"ActivityId\":\"1.103\",\"ActivityName\":\"Log Message\",\"IsTransient\":false},{\"ConditionalExpression\":null,\"ActionExpression\":null,\"ExpectedHitCounter\":null,\"ShouldContinueAfterAction\":false,\"BreakpointType\":1,\"LocationIdentifier\":\"ConvertLineItemFromMappings - Invoke Workflow File (Restaurent365\\\\\\\\ConvertLineItemFromMappings.xaml)\",\"IsEnabled\":true,\"Annotation\":null,\"Id\":\"1da41203-9a9d-401e-b59f-892084546611\",\"ActivityIdRef\":\"InvokeWorkflowFile_1\",\"ActivityId\":null,\"ActivityName\":\"ConvertLineItemFromMappings - Invoke Workflow File (Restaurent365\\\\\\\\ConvertLineItemFromMappings.xaml)\",\"IsTransient\":false}],\"Restaurent365/ConvertLineItemFromMappings.xaml\":[{\"ConditionalExpression\":null,\"ActionExpression\":null,\"ExpectedHitCounter\":null,\"ShouldContinueAfterAction\":false,\"BreakpointType\":1,\"LocationIdentifier\":\"Else If\",\"IsEnabled\":true,\"Annotation\":null,\"Id\":\"0262cc2a-4ae8-4be7-a864-4f30a69beb83\",\"ActivityIdRef\":\"IfElseIfV2_1\",\"ActivityId\":\"1.206\",\"ActivityName\":\"Else If\",\"IsTransient\":false},{\"ConditionalExpression\":null,\"ActionExpression\":null,\"ExpectedHitCounter\":null,\"ShouldContinueAfterAction\":false,\"BreakpointType\":1,\"LocationIdentifier\":\"If\",\"IsEnabled\":false,\"Annotation\":null,\"Id\":\"ea23398a-4ca8-4350-87d3-14f23da1276a\",\"ActivityIdRef\":\"If_1\",\"ActivityId\":\"1.6\",\"ActivityName\":\"If\",\"IsTransient\":false},{\"ConditionalExpression\":null,\"ActionExpression\":null,\"ExpectedHitCounter\":null,\"ShouldContinueAfterAction\":false,\"BreakpointType\":1,\"LocationIdentifier\":\"For Each currentIinetems\",\"IsEnabled\":true,\"Annotation\":null,\"Id\":\"2605cedc-2dc8-4cbd-ac38-b2ca24014827\",\"ActivityIdRef\":\"ForEach`1_2\",\"ActivityId\":\"1.4\",\"ActivityName\":\"For Each currentIinetems\",\"IsTransient\":false}],\"Restaurent365/ConvertLineItemFromMappingsDuModel2.xaml\":[{\"ConditionalExpression\":null,\"ActionExpression\":null,\"ExpectedHitCounter\":null,\"ShouldContinueAfterAction\":false,\"BreakpointType\":1,\"LocationIdentifier\":\"Extract Document Data\",\"IsEnabled\":false,\"Annotation\":null,\"Id\":\"f0b20e62-2de0-4063-94d9-15e0ee7d28fd\",\"ActivityIdRef\":\"ExtractDocumentDataWithDocumentData`1_1\",\"ActivityId\":\"1.456\",\"ActivityName\":\"Extract Document Data\",\"IsTransient\":false},{\"ConditionalExpression\":null,\"ActionExpression\":null,\"ExpectedHitCounter\":null,\"ShouldContinueAfterAction\":false,\"BreakpointType\":1,\"LocationIdentifier\":\"Else If\",\"IsEnabled\":true,\"Annotation\":null,\"Id\":\"d2326112-5542-4ef4-97d1-12610c03fb19\",\"ActivityIdRef\":\"IfElseIfV2_1\",\"ActivityId\":\"1.395\",\"ActivityName\":\"Else If\",\"IsTransient\":false},{\"ConditionalExpression\":null,\"ActionExpression\":null,\"ExpectedHitCounter\":null,\"ShouldContinueAfterAction\":false,\"BreakpointType\":1,\"LocationIdentifier\":\"Add Data Row\",\"IsEnabled\":false,\"Annotation\":null,\"Id\":\"eef25276-ba9a-4874-a038-6e62b9bead0f\",\"ActivityIdRef\":\"AddDataRow_1\",\"ActivityId\":\"1.184\",\"ActivityName\":\"Add Data Row\",\"IsTransient\":false},{\"ConditionalExpression\":null,\"ActionExpression\":null,\"ExpectedHitCounter\":null,\"ShouldContinueAfterAction\":false,\"BreakpointType\":1,\"LocationIdentifier\":\"For Each currentIinetems\",\"IsEnabled\":true,\"Annotation\":null,\"Id\":\"e8b5e073-0a5c-4fb0-a13f-b0b70a55e99b\",\"ActivityIdRef\":\"ForEach`1_2\",\"ActivityId\":\"1.4\",\"ActivityName\":\"For Each currentIinetems\",\"IsTransient\":false}]},\"CodeBreakpoints\":{}}","Compiler":"2","ProjectWatches":"{\"Value\":[]}","OpenedDocuments":"[{\"DocumentPath\":\"Main.xaml\",\"FactoryId\":\"{ACB8E7BA-F093-44C1-9B50-33ECA51AAE16}\"},{\"DocumentPath\":\"TestExtraction/TextExtractionData.xaml\",\"FactoryId\":\"{ACB8E7BA-F093-44C1-9B50-33ECA51AAE16}\"}]","ProjectActivitiesViewState":"{\"Gmail/ProcessGmails.xaml\":[{\"ActivityIdRef\":\"DeserializeJson`1_2\",\"IsAdvancedOptionsExpanded\":false,\"Categories\":{\"Input\":true,\"Output\":true},\"Widgets\":{}},{\"ActivityIdRef\":\"InvokeWorkflowFile_8\",\"IsAdvancedOptionsExpanded\":false,\"Categories\":{\"Common\":true,\"Options\":true,\"Log\":true,\"Output\":true},\"Widgets\":{}},{\"ActivityIdRef\":\"ForEachEmailConnections_1\",\"IsAdvancedOptionsExpanded\":false,\"Categories\":{\"Options\":true,\"Output\":true},\"Widgets\":{\"Body\":{\"ShowExpanded\":true}}},{\"ActivityIdRef\":\"TryCatch_1\",\"IsAdvancedOptionsExpanded\":false,\"Widgets\":{\"Try\":{\"ShowExpanded\":true},\"Finally\":{\"ShowExpanded\":true}}},{\"ActivityIdRef\":\"If_2\",\"IsAdvancedOptionsExpanded\":false,\"Widgets\":{\"Then\":{\"ShowExpanded\":true},\"Else\":{\"ShowExpanded\":true}}},{\"ActivityIdRef\":\"If_7\",\"IsAdvancedOptionsExpanded\":false,\"Widgets\":{\"Then\":{\"ShowExpanded\":true},\"Else\":{\"ShowExpanded\":true}}},{\"ActivityIdRef\":\"If_1\",\"IsAdvancedOptionsExpanded\":false,\"Widgets\":{\"Then\":{\"ShowExpanded\":true},\"Else\":{\"ShowExpanded\":true}}},{\"ActivityIdRef\":\"DownloadAttachmentsConnections_1\",\"IsAdvancedOptionsExpanded\":false,\"Categories\":{\"Output\":true,\"Options\":true},\"Widgets\":{}},{\"ActivityIdRef\":\"If_6\",\"IsAdvancedOptionsExpanded\":false,\"Widgets\":{\"Then\":{\"ShowExpanded\":true},\"Else\":{\"ShowExpanded\":true}}},{\"ActivityIdRef\":\"LogMessage_9\",\"IsAdvancedOptionsExpanded\":false,\"Widgets\":{}},{\"ActivityIdRef\":\"If_8\",\"IsAdvancedOptionsExpanded\":false,\"Widgets\":{\"Then\":{\"ShowExpanded\":true},\"Else\":{\"ShowExpanded\":true}}},{\"ActivityIdRef\":\"ForEach`1_1\",\"IsAdvancedOptionsExpanded\":false,\"Categories\":{\"\":true},\"Widgets\":{\"Body\":{\"ShowExpanded\":true}}},{\"ActivityIdRef\":\"ExtractDocumentDataWithDocumentData`1_4\",\"IsAdvancedOptionsExpanded\":false,\"Categories\":{\"Input\":true,\"Output\":true},\"Widgets\":{}},{\"ActivityIdRef\":\"If_13\",\"IsAdvancedOptionsExpanded\":false,\"Widgets\":{\"Then\":{\"ShowExpanded\":true},\"Else\":{\"ShowExpanded\":true}}},{\"ActivityIdRef\":\"If_3\",\"IsAdvancedOptionsExpanded\":false,\"Widgets\":{\"Then\":{\"ShowExpanded\":true},\"Else\":{\"ShowExpanded\":true}}},{\"ActivityIdRef\":\"IfElseIfV2_1\",\"IsAdvancedOptionsExpanded\":false,\"Widgets\":{\"Then\":{\"ShowExpanded\":true},\"Else\":{\"ShowExpanded\":true}}},{\"ActivityIdRef\":\"Break_1\",\"IsAdvancedOptionsExpanded\":false,\"Widgets\":{}},{\"ActivityIdRef\":\"LogMessage_2\",\"IsAdvancedOptionsExpanded\":false,\"Widgets\":{}},{\"ActivityIdRef\":\"If_10\",\"IsAdvancedOptionsExpanded\":false,\"Widgets\":{\"Then\":{\"ShowExpanded\":true},\"Else\":{\"ShowExpanded\":true}}},{\"ActivityIdRef\":\"MoveEmailConnections_3\",\"IsAdvancedOptionsExpanded\":false,\"Categories\":{\"Output\":true},\"Widgets\":{}},{\"ActivityIdRef\":\"LogMessage_3\",\"IsAdvancedOptionsExpanded\":false,\"Widgets\":{}},{\"ActivityIdRef\":\"LogMessage_7\",\"IsAdvancedOptionsExpanded\":false,\"Widgets\":{}},{\"ActivityIdRef\":\"AddDataRow_2\",\"IsAdvancedOptionsExpanded\":false,\"Widgets\":{}},{\"ActivityIdRef\":\"MoveEmailConnections_2\",\"IsAdvancedOptionsExpanded\":false,\"Categories\":{\"Output\":true},\"Widgets\":{}},{\"ActivityIdRef\":\"LogMessage_4\",\"IsAdvancedOptionsExpanded\":false,\"Widgets\":{}},{\"ActivityIdRef\":\"If_4\",\"IsAdvancedOptionsExpanded\":false,\"Widgets\":{\"Then\":{\"ShowExpanded\":true},\"Else\":{\"ShowExpanded\":true}}},{\"ActivityIdRef\":\"MoveEmailConnections_1\",\"IsAdvancedOptionsExpanded\":false,\"Categories\":{\"Output\":true},\"Widgets\":{}},{\"ActivityIdRef\":\"AddDataRow_4\",\"IsAdvancedOptionsExpanded\":false,\"Widgets\":{}},{\"ActivityIdRef\":\"InvokeWorkflowFile_10\",\"IsAdvancedOptionsExpanded\":false,\"Categories\":{\"Common\":true,\"Options\":true,\"Log\":true,\"Output\":true},\"Widgets\":{}},{\"ActivityIdRef\":\"LogMessage_8\",\"IsAdvancedOptionsExpanded\":false,\"Widgets\":{}},{\"ActivityIdRef\":\"AddDataRow_3\",\"IsAdvancedOptionsExpanded\":false,\"Widgets\":{}},{\"ActivityIdRef\":\"LogMessage_10\",\"IsAdvancedOptionsExpanded\":false,\"Widgets\":{}},{\"ActivityIdRef\":\"Continue_2\",\"IsAdvancedOptionsExpanded\":false,\"Widgets\":{}},{\"ActivityIdRef\":\"LogMessage_6\",\"IsAdvancedOptionsExpanded\":false,\"Widgets\":{}},{\"ActivityIdRef\":\"Continue_1\",\"IsAdvancedOptionsExpanded\":false,\"Widgets\":{}},{\"ActivityIdRef\":\"LogMessage_5\",\"IsAdvancedOptionsExpanded\":false,\"Widgets\":{}},{\"ActivityIdRef\":\"Sequence_1\",\"IsAdvancedOptionsExpanded\":false,\"Widgets\":{}},{\"ActivityIdRef\":\"<>c_1\",\"IsAdvancedOptionsExpanded\":false,\"Widgets\":{}},{\"ActivityIdRef\":\"Sequence_19\",\"IsAdvancedOptionsExpanded\":false,\"Widgets\":{}},{\"ActivityIdRef\":\"ReadTextFile_2\",\"IsAdvancedOptionsExpanded\":false,\"Widgets\":{}},{\"ActivityIdRef\":\"Assign_3\",\"IsAdvancedOptionsExpanded\":false,\"Widgets\":{}},{\"ActivityIdRef\":\"CommentOut_9\",\"IsAdvancedOptionsExpanded\":false,\"Widgets\":{}},{\"ActivityIdRef\":\"Sequence_50\",\"IsAdvancedOptionsExpanded\":false,\"Widgets\":{}},{\"ActivityIdRef\":\"Assign_4\",\"IsAdvancedOptionsExpanded\":false,\"Widgets\":{}},{\"ActivityIdRef\":\"CommentOut_2\",\"IsAdvancedOptionsExpanded\":false,\"Widgets\":{}},{\"ActivityIdRef\":\"Sequence_21\",\"IsAdvancedOptionsExpanded\":false,\"Widgets\":{}},{\"ActivityIdRef\":\"Assign_6\",\"IsAdvancedOptionsExpanded\":false,\"Widgets\":{}},{\"ActivityIdRef\":\"CommentOut_1\",\"IsAdvancedOptionsExpanded\":false,\"Widgets\":{}},{\"ActivityIdRef\":\"Sequence_22\",\"IsAdvancedOptionsExpanded\":false,\"Widgets\":{}},{\"ActivityIdRef\":\"Assign_10\",\"IsAdvancedOptionsExpanded\":false,\"Widgets\":{}},{\"ActivityIdRef\":\"ReadCsvFile_2\",\"IsAdvancedOptionsExpanded\":false,\"Widgets\":{}},{\"ActivityIdRef\":\"ReadCsvFile_3\",\"IsAdvancedOptionsExpanded\":false,\"Widgets\":{}},{\"ActivityIdRef\":\"Assign_18\",\"IsAdvancedOptionsExpanded\":false,\"Widgets\":{}},{\"ActivityIdRef\":\"BuildDataTable_1\",\"IsAdvancedOptionsExpanded\":false,\"Widgets\":{}},{\"ActivityIdRef\":\"Assign_15\",\"IsAdvancedOptionsExpanded\":false,\"Widgets\":{}},{\"ActivityIdRef\":\"Sequence_2\",\"IsAdvancedOptionsExpanded\":false,\"Widgets\":{}},{\"ActivityIdRef\":\"Sequence_4\",\"IsAdvancedOptionsExpanded\":false,\"Widgets\":{}},{\"ActivityIdRef\":\"Sequence_9\",\"IsAdvancedOptionsExpanded\":false,\"Widgets\":{}},{\"ActivityIdRef\":\"CommentOut_3\",\"IsAdvancedOptionsExpanded\":false,\"Widgets\":{}},{\"ActivityIdRef\":\"Sequence_23\",\"IsAdvancedOptionsExpanded\":false,\"Widgets\":{}},{\"ActivityIdRef\":\"AddDataRow_1\",\"IsAdvancedOptionsExpanded\":false,\"Widgets\":{}},{\"ActivityIdRef\":\"Sequence_10\",\"IsAdvancedOptionsExpanded\":false,\"Widgets\":{}},{\"ActivityIdRef\":\"Sequence_31\",\"IsAdvancedOptionsExpanded\":false,\"Widgets\":{}},{\"ActivityIdRef\":\"CommentOut_6\",\"IsAdvancedOptionsExpanded\":false,\"Widgets\":{}},{\"ActivityIdRef\":\"Sequence_30\",\"IsAdvancedOptionsExpanded\":false,\"Widgets\":{}},{\"ActivityIdRef\":\"AddDataRow_5\",\"IsAdvancedOptionsExpanded\":false,\"Widgets\":{}},{\"ActivityIdRef\":\"Sequence_32\",\"IsAdvancedOptionsExpanded\":false,\"Widgets\":{}},{\"ActivityIdRef\":\"PathExists_2\",\"IsAdvancedOptionsExpanded\":false,\"Widgets\":{}},{\"ActivityIdRef\":\"Sequence_7\",\"IsAdvancedOptionsExpanded\":false,\"Widgets\":{}},{\"ActivityIdRef\":\"CreateDirectory_1\",\"IsAdvancedOptionsExpanded\":false,\"Widgets\":{}},{\"ActivityIdRef\":\"Sequence_8\",\"IsAdvancedOptionsExpanded\":false,\"Widgets\":{}},{\"ActivityIdRef\":\"Sequence_26\",\"IsAdvancedOptionsExpanded\":false,\"Widgets\":{}},{\"ActivityIdRef\":\"Sequence_27\",\"IsAdvancedOptionsExpanded\":false,\"Widgets\":{}},{\"ActivityIdRef\":\"Sequence_6\",\"IsAdvancedOptionsExpanded\":false,\"Widgets\":{}},{\"ActivityIdRef\":\"Comment_1\",\"IsAdvancedOptionsExpanded\":false,\"Widgets\":{}},{\"ActivityIdRef\":\"Assign_21\",\"IsAdvancedOptionsExpanded\":false,\"Widgets\":{}},{\"ActivityIdRef\":\"Assign_11\",\"IsAdvancedOptionsExpanded\":false,\"Widgets\":{}},{\"ActivityIdRef\":\"Sequence_44\",\"IsAdvancedOptionsExpanded\":false,\"Widgets\":{}},{\"ActivityIdRef\":\"Assign_16\",\"IsAdvancedOptionsExpanded\":false,\"Widgets\":{}},{\"ActivityIdRef\":\"Sequence_45\",\"IsAdvancedOptionsExpanded\":false,\"Widgets\":{}},{\"ActivityIdRef\":\"Sequence_12\",\"IsAdvancedOptionsExpanded\":false,\"Widgets\":{}},{\"ActivityIdRef\":\"Sequence_46\",\"IsAdvancedOptionsExpanded\":false,\"Widgets\":{}},{\"ActivityIdRef\":\"Assign_12\",\"IsAdvancedOptionsExpanded\":false,\"Widgets\":{}},{\"ActivityIdRef\":\"IfElseIfBlock_1\",\"IsAdvancedOptionsExpanded\":false,\"Widgets\":{}},{\"ActivityIdRef\":\"Sequence_47\",\"IsAdvancedOptionsExpanded\":false,\"Widgets\":{}},{\"ActivityIdRef\":\"Assign_17\",\"IsAdvancedOptionsExpanded\":false,\"Widgets\":{}},{\"ActivityIdRef\":\"Sequence_48\",\"IsAdvancedOptionsExpanded\":false,\"Widgets\":{}},{\"ActivityIdRef\":\"Sequence_49\",\"IsAdvancedOptionsExpanded\":false,\"Widgets\":{}},{\"ActivityIdRef\":\"Assign_7\",\"IsAdvancedOptionsExpanded\":false,\"Widgets\":{}},{\"ActivityIdRef\":\"Assign_8\",\"IsAdvancedOptionsExpanded\":false,\"Widgets\":{}},{\"ActivityIdRef\":\"Assign_20\",\"IsAdvancedOptionsExpanded\":false,\"Widgets\":{}},{\"ActivityIdRef\":\"Assign_13\",\"IsAdvancedOptionsExpanded\":false,\"Widgets\":{}},{\"ActivityIdRef\":\"Assign_9\",\"IsAdvancedOptionsExpanded\":false,\"Widgets\":{}},{\"ActivityIdRef\":\"Sequence_15\",\"IsAdvancedOptionsExpanded\":false,\"Widgets\":{}},{\"ActivityIdRef\":\"Sequence_16\",\"IsAdvancedOptionsExpanded\":false,\"Widgets\":{}},{\"ActivityIdRef\":\"CommentOut_5\",\"IsAdvancedOptionsExpanded\":false,\"Widgets\":{}},{\"ActivityIdRef\":\"Sequence_29\",\"IsAdvancedOptionsExpanded\":false,\"Widgets\":{}},{\"ActivityIdRef\":\"ApplyEmailLabelsConnections_4\",\"IsAdvancedOptionsExpanded\":false,\"Widgets\":{}},{\"ActivityIdRef\":\"Sequence_51\",\"IsAdvancedOptionsExpanded\":false,\"Widgets\":{}},{\"ActivityIdRef\":\"Sequence_13\",\"IsAdvancedOptionsExpanded\":false,\"Widgets\":{}},{\"ActivityIdRef\":\"Assign_14\",\"IsAdvancedOptionsExpanded\":false,\"Widgets\":{}},{\"ActivityIdRef\":\"CommentOut_4\",\"IsAdvancedOptionsExpanded\":false,\"Widgets\":{}},{\"ActivityIdRef\":\"Sequence_28\",\"IsAdvancedOptionsExpanded\":false,\"Widgets\":{}},{\"ActivityIdRef\":\"ApplyEmailLabelsConnections_3\",\"IsAdvancedOptionsExpanded\":false,\"Widgets\":{}},{\"ActivityIdRef\":\"Sequence_52\",\"IsAdvancedOptionsExpanded\":false,\"Widgets\":{}},{\"ActivityIdRef\":\"Sequence_37\",\"IsAdvancedOptionsExpanded\":false,\"Widgets\":{}},{\"ActivityIdRef\":\"MoveFile_1\",\"IsAdvancedOptionsExpanded\":false,\"Widgets\":{}},{\"ActivityIdRef\":\"Sequence_38\",\"IsAdvancedOptionsExpanded\":false,\"Widgets\":{}},{\"ActivityIdRef\":\"Comment_2\",\"IsAdvancedOptionsExpanded\":false,\"Widgets\":{}},{\"ActivityIdRef\":\"CatchList_1\",\"IsAdvancedOptionsExpanded\":false,\"Widgets\":{}},{\"ActivityIdRef\":\"Catch`1_3\",\"IsAdvancedOptionsExpanded\":false,\"Widgets\":{}},{\"ActivityIdRef\":\"Sequence_3\",\"IsAdvancedOptionsExpanded\":false,\"Widgets\":{}},{\"ActivityIdRef\":\"MoveEmailConnections_4\",\"IsAdvancedOptionsExpanded\":false,\"Categories\":{\"Output\":true},\"Widgets\":{}},{\"ActivityIdRef\":\"Sequence_53\",\"IsAdvancedOptionsExpanded\":false,\"Widgets\":{}},{\"ActivityIdRef\":\"<>c_2\",\"IsAdvancedOptionsExpanded\":false,\"Widgets\":{}},{\"ActivityIdRef\":\"Sequence_5\",\"IsAdvancedOptionsExpanded\":false,\"Widgets\":{}},{\"ActivityIdRef\":\"Sequence_34\",\"IsAdvancedOptionsExpanded\":false,\"Widgets\":{}},{\"ActivityIdRef\":\"Sequence_33\",\"IsAdvancedOptionsExpanded\":false,\"Widgets\":{}},{\"ActivityIdRef\":\"CreateFile_2\",\"IsAdvancedOptionsExpanded\":false,\"Widgets\":{}},{\"ActivityIdRef\":\"WriteCsvFile_1\",\"IsAdvancedOptionsExpanded\":false,\"Widgets\":{}},{\"ActivityIdRef\":\"If_14\",\"IsAdvancedOptionsExpanded\":false,\"Widgets\":{\"Then\":{\"ShowExpanded\":true},\"Else\":{\"ShowExpanded\":true}}},{\"ActivityIdRef\":\"Sequence_43\",\"IsAdvancedOptionsExpanded\":false,\"Widgets\":{}},{\"ActivityIdRef\":\"If_11\",\"IsAdvancedOptionsExpanded\":false,\"Widgets\":{\"Then\":{\"ShowExpanded\":true},\"Else\":{\"ShowExpanded\":true}}},{\"ActivityIdRef\":\"Sequence_39\",\"IsAdvancedOptionsExpanded\":false,\"Widgets\":{}},{\"ActivityIdRef\":\"SendEmailConnections_1\",\"IsAdvancedOptionsExpanded\":false,\"Categories\":{\"Recipients\":true,\"Options\":true},\"Widgets\":{}},{\"ActivityIdRef\":\"Sequence_40\",\"IsAdvancedOptionsExpanded\":false,\"Widgets\":{}},{\"ActivityIdRef\":\"SendEmailConnections_3\",\"IsAdvancedOptionsExpanded\":false,\"Categories\":{\"Recipients\":true,\"Options\":true},\"Widgets\":{}},{\"ActivityIdRef\":\"MoveEmailConnections_7\",\"IsAdvancedOptionsExpanded\":false,\"Categories\":{\"Output\":true},\"Widgets\":{}},{\"ActivityIdRef\":\"MoveEmailConnections_5\",\"IsAdvancedOptionsExpanded\":false,\"Categories\":{\"Output\":true},\"Widgets\":{}},{\"ActivityIdRef\":\"ExtractDocumentDataWithDocumentData`1_5\",\"IsAdvancedOptionsExpanded\":false,\"Categories\":{\"Input\":true,\"Output\":true},\"Widgets\":{}},{\"ActivityIdRef\":\"MoveEmailConnections_6\",\"IsAdvancedOptionsExpanded\":false,\"Categories\":{\"Output\":true},\"Widgets\":{}},{\"ActivityIdRef\":\"If_15\",\"IsAdvancedOptionsExpanded\":false,\"Widgets\":{\"Then\":{\"ShowExpanded\":true},\"Else\":{\"ShowExpanded\":true}}},{\"ActivityIdRef\":\"Continue_3\",\"IsAdvancedOptionsExpanded\":false,\"Widgets\":{}},{\"ActivityIdRef\":\"Assign_25\",\"IsAdvancedOptionsExpanded\":false,\"Widgets\":{}},{\"ActivityIdRef\":\"Sequence_57\",\"IsAdvancedOptionsExpanded\":false,\"Widgets\":{}},{\"ActivityIdRef\":\"Sequence_58\",\"IsAdvancedOptionsExpanded\":false,\"Widgets\":{}},{\"ActivityIdRef\":\"IfElseIfBlock_2\",\"IsAdvancedOptionsExpanded\":false,\"Widgets\":{}},{\"ActivityIdRef\":\"Sequence_55\",\"IsAdvancedOptionsExpanded\":false,\"Widgets\":{}},{\"ActivityIdRef\":\"Assign_22\",\"IsAdvancedOptionsExpanded\":false,\"Widgets\":{}},{\"ActivityIdRef\":\"Assign_23\",\"IsAdvancedOptionsExpanded\":false,\"Widgets\":{}},{\"ActivityIdRef\":\"IfElseIfBlock_3\",\"IsAdvancedOptionsExpanded\":false,\"Widgets\":{}},{\"ActivityIdRef\":\"Sequence_56\",\"IsAdvancedOptionsExpanded\":false,\"Widgets\":{}},{\"ActivityIdRef\":\"Assign_24\",\"IsAdvancedOptionsExpanded\":false,\"Widgets\":{}},{\"ActivityIdRef\":\"Assign_26\",\"IsAdvancedOptionsExpanded\":false,\"Widgets\":{}},{\"ActivityIdRef\":\"Sequence_59\",\"IsAdvancedOptionsExpanded\":false,\"Widgets\":{}},{\"ActivityIdRef\":\"Sequence_60\",\"IsAdvancedOptionsExpanded\":false,\"Widgets\":{}},{\"ActivityIdRef\":\"Sequence_61\",\"IsAdvancedOptionsExpanded\":false,\"Widgets\":{}},{\"ActivityIdRef\":\"CommentOut_13\",\"IsAdvancedOptionsExpanded\":false,\"Widgets\":{}},{\"ActivityIdRef\":\"Sequence_54\",\"IsAdvancedOptionsExpanded\":false,\"Widgets\":{}},{\"ActivityIdRef\":\"MoveEmailConnections_9\",\"IsAdvancedOptionsExpanded\":false,\"Categories\":{\"Output\":true},\"Widgets\":{}},{\"ActivityIdRef\":\"MoveEmailConnections_8\",\"IsAdvancedOptionsExpanded\":false,\"Categories\":{\"Output\":true},\"Widgets\":{}},{\"ActivityIdRef\":\"MoveEmailConnections_10\",\"IsAdvancedOptionsExpanded\":false,\"Categories\":{\"Output\":true},\"Widgets\":{}},{\"ActivityIdRef\":\"Assign_28\",\"IsAdvancedOptionsExpanded\":false,\"Widgets\":{}},{\"ActivityIdRef\":\"Assign_27\",\"IsAdvancedOptionsExpanded\":false,\"Widgets\":{}},{\"ActivityIdRef\":\"If_16\",\"IsAdvancedOptionsExpanded\":false,\"Widgets\":{\"Then\":{\"ShowExpanded\":true},\"Else\":{\"ShowExpanded\":true}}},{\"ActivityIdRef\":\"AddDataRow_6\",\"IsAdvancedOptionsExpanded\":false,\"Widgets\":{}},{\"ActivityIdRef\":\"LogMessage_11\",\"IsAdvancedOptionsExpanded\":false,\"Widgets\":{}}],\"Restaurent365/ProcessInvoice.xaml\":[{\"ActivityIdRef\":\"If_7\",\"IsAdvancedOptionsExpanded\":false,\"Widgets\":{\"Then\":{\"ShowExpanded\":true},\"Else\":{\"ShowExpanded\":true}}},{\"ActivityIdRef\":\"If_1\",\"IsAdvancedOptionsExpanded\":false,\"Widgets\":{\"Then\":{\"ShowExpanded\":true},\"Else\":{\"ShowExpanded\":true}}},{\"ActivityIdRef\":\"LogMessage_7\",\"IsAdvancedOptionsExpanded\":false,\"Widgets\":{}},{\"ActivityIdRef\":\"If_8\",\"IsAdvancedOptionsExpanded\":false,\"Widgets\":{\"Then\":{\"ShowExpanded\":true},\"Else\":{\"ShowExpanded\":true}}},{\"ActivityIdRef\":\"LogMessage_9\",\"IsAdvancedOptionsExpanded\":false,\"Widgets\":{}},{\"ActivityIdRef\":\"InvokeWorkflowFile_1\",\"IsAdvancedOptionsExpanded\":false,\"Categories\":{\"Common\":true,\"Options\":true,\"Log\":true,\"Output\":true},\"Widgets\":{}},{\"ActivityIdRef\":\"LogMessage_2\",\"IsAdvancedOptionsExpanded\":false,\"Widgets\":{}},{\"ActivityIdRef\":\"ForEach`1_1\",\"IsAdvancedOptionsExpanded\":false,\"Categories\":{\"\":true},\"Widgets\":{\"Body\":{\"ShowExpanded\":true}}},{\"ActivityIdRef\":\"If_9\",\"IsAdvancedOptionsExpanded\":false,\"Widgets\":{\"Then\":{\"ShowExpanded\":true},\"Else\":{\"ShowExpanded\":true}}},{\"ActivityIdRef\":\"LogMessage_10\",\"IsAdvancedOptionsExpanded\":false,\"Widgets\":{}},{\"ActivityIdRef\":\"LogMessage_1\",\"IsAdvancedOptionsExpanded\":false,\"Widgets\":{}},{\"ActivityIdRef\":\"If_10\",\"IsAdvancedOptionsExpanded\":false,\"Widgets\":{\"Then\":{\"ShowExpanded\":true},\"Else\":{\"ShowExpanded\":true}}},{\"ActivityIdRef\":\"If_4\",\"IsAdvancedOptionsExpanded\":false,\"Widgets\":{\"Then\":{\"ShowExpanded\":true},\"Else\":{\"ShowExpanded\":true}}},{\"ActivityIdRef\":\"LogMessage_8\",\"IsAdvancedOptionsExpanded\":false,\"Widgets\":{}},{\"ActivityIdRef\":\"Break_2\",\"IsAdvancedOptionsExpanded\":false,\"Widgets\":{}},{\"ActivityIdRef\":\"If_11\",\"IsAdvancedOptionsExpanded\":false,\"Widgets\":{\"Then\":{\"ShowExpanded\":true},\"Else\":{\"ShowExpanded\":true}}},{\"ActivityIdRef\":\"If_5\",\"IsAdvancedOptionsExpanded\":false,\"Widgets\":{\"Then\":{\"ShowExpanded\":true},\"Else\":{\"ShowExpanded\":true}}},{\"ActivityIdRef\":\"LogMessage_3\",\"IsAdvancedOptionsExpanded\":false,\"Widgets\":{}},{\"ActivityIdRef\":\"Return_1\",\"IsAdvancedOptionsExpanded\":false,\"Widgets\":{}},{\"ActivityIdRef\":\"Sequence_1\",\"IsAdvancedOptionsExpanded\":false,\"Widgets\":{}},{\"ActivityIdRef\":\"<>c_1\",\"IsAdvancedOptionsExpanded\":false,\"Widgets\":{}},{\"ActivityIdRef\":\"NApplicationCard_3\",\"IsAdvancedOptionsExpanded\":false,\"Widgets\":{}},{\"ActivityIdRef\":\"Sequence_5\",\"IsAdvancedOptionsExpanded\":false,\"Widgets\":{}},{\"ActivityIdRef\":\"NGetAttributeGeneric`1_1\",\"IsAdvancedOptionsExpanded\":false,\"Widgets\":{}},{\"ActivityIdRef\":\"Sequence_34\",\"IsAdvancedOptionsExpanded\":false,\"Widgets\":{}},{\"ActivityIdRef\":\"NClick_10\",\"IsAdvancedOptionsExpanded\":false,\"Widgets\":{}},{\"ActivityIdRef\":\"Sequence_35\",\"IsAdvancedOptionsExpanded\":false,\"Widgets\":{}},{\"ActivityIdRef\":\"NGoToUrl_1\",\"IsAdvancedOptionsExpanded\":false,\"Widgets\":{}},{\"ActivityIdRef\":\"ReadCsvFile_1\",\"IsAdvancedOptionsExpanded\":false,\"Widgets\":{}},{\"ActivityIdRef\":\"Sequence_27\",\"IsAdvancedOptionsExpanded\":false,\"Widgets\":{}},{\"ActivityIdRef\":\"NTypeInto_1\",\"IsAdvancedOptionsExpanded\":false,\"Widgets\":{}},{\"ActivityIdRef\":\"NTypeInto_2\",\"IsAdvancedOptionsExpanded\":false,\"Widgets\":{}},{\"ActivityIdRef\":\"NClick_1\",\"IsAdvancedOptionsExpanded\":false,\"Widgets\":{}},{\"ActivityIdRef\":\"Sequence_29\",\"IsAdvancedOptionsExpanded\":false,\"Widgets\":{}},{\"ActivityIdRef\":\"UiElementExists_4\",\"IsAdvancedOptionsExpanded\":false,\"Widgets\":{}},{\"ActivityIdRef\":\"Sequence_9\",\"IsAdvancedOptionsExpanded\":false,\"Widgets\":{}},{\"ActivityIdRef\":\"Assign_2\",\"IsAdvancedOptionsExpanded\":false,\"Widgets\":{}},{\"ActivityIdRef\":\"Sequence_8\",\"IsAdvancedOptionsExpanded\":false,\"Widgets\":{}},{\"ActivityIdRef\":\"NTypeInto_3\",\"IsAdvancedOptionsExpanded\":false,\"Widgets\":{}},{\"ActivityIdRef\":\"NTypeInto_4\",\"IsAdvancedOptionsExpanded\":false,\"Widgets\":{}},{\"ActivityIdRef\":\"NTypeInto_7\",\"IsAdvancedOptionsExpanded\":false,\"Widgets\":{}},{\"ActivityIdRef\":\"NTypeInto_5\",\"IsAdvancedOptionsExpanded\":false,\"Widgets\":{}},{\"ActivityIdRef\":\"Sequence_28\",\"IsAdvancedOptionsExpanded\":false,\"Widgets\":{}},{\"ActivityIdRef\":\"If_6\",\"IsAdvancedOptionsExpanded\":false,\"Widgets\":{\"Then\":{\"ShowExpanded\":true},\"Else\":{\"ShowExpanded\":true}}},{\"ActivityIdRef\":\"Sequence_32\",\"IsAdvancedOptionsExpanded\":false,\"Widgets\":{}},{\"ActivityIdRef\":\"NClick_5\",\"IsAdvancedOptionsExpanded\":false,\"Widgets\":{}},{\"ActivityIdRef\":\"TypeInto_2\",\"IsAdvancedOptionsExpanded\":false,\"Widgets\":{}},{\"ActivityIdRef\":\"NClick_6\",\"IsAdvancedOptionsExpanded\":false,\"Widgets\":{}},{\"ActivityIdRef\":\"Sequence_33\",\"IsAdvancedOptionsExpanded\":false,\"Widgets\":{}},{\"ActivityIdRef\":\"Sequence_43\",\"IsAdvancedOptionsExpanded\":false,\"Widgets\":{}},{\"ActivityIdRef\":\"Sequence_6\",\"IsAdvancedOptionsExpanded\":false,\"Widgets\":{}},{\"ActivityIdRef\":\"Assign_5\",\"IsAdvancedOptionsExpanded\":false,\"Widgets\":{}},{\"ActivityIdRef\":\"Sequence_39\",\"IsAdvancedOptionsExpanded\":false,\"Widgets\":{}},{\"ActivityIdRef\":\"Assign_6\",\"IsAdvancedOptionsExpanded\":false,\"Widgets\":{}},{\"ActivityIdRef\":\"Sequence_40\",\"IsAdvancedOptionsExpanded\":false,\"Widgets\":{}},{\"ActivityIdRef\":\"Sequence_41\",\"IsAdvancedOptionsExpanded\":false,\"Widgets\":{}},{\"ActivityIdRef\":\"NTypeInto_12\",\"IsAdvancedOptionsExpanded\":false,\"Widgets\":{}},{\"ActivityIdRef\":\"NClick_17\",\"IsAdvancedOptionsExpanded\":false,\"Widgets\":{}},{\"ActivityIdRef\":\"NTypeInto_13\",\"IsAdvancedOptionsExpanded\":false,\"Widgets\":{}},{\"ActivityIdRef\":\"Sequence_42\",\"IsAdvancedOptionsExpanded\":false,\"Widgets\":{}},{\"ActivityIdRef\":\"NTypeInto_11\",\"IsAdvancedOptionsExpanded\":false,\"Widgets\":{}},{\"ActivityIdRef\":\"NClick_14\",\"IsAdvancedOptionsExpanded\":false,\"Widgets\":{}},{\"ActivityIdRef\":\"NClick_13\",\"IsAdvancedOptionsExpanded\":false,\"Widgets\":{}},{\"ActivityIdRef\":\"Sequence_7\",\"IsAdvancedOptionsExpanded\":false,\"Widgets\":{}},{\"ActivityIdRef\":\"Sequence_37\",\"IsAdvancedOptionsExpanded\":false,\"Widgets\":{}},{\"ActivityIdRef\":\"Assign_4\",\"IsAdvancedOptionsExpanded\":false,\"Widgets\":{}},{\"ActivityIdRef\":\"Sequence_38\",\"IsAdvancedOptionsExpanded\":false,\"Widgets\":{}},{\"ActivityIdRef\":\"Comment_1\",\"IsAdvancedOptionsExpanded\":false,\"Widgets\":{}},{\"ActivityIdRef\":\"Sequence_13\",\"IsAdvancedOptionsExpanded\":false,\"Widgets\":{}},{\"ActivityIdRef\":\"NTypeInto_8\",\"IsAdvancedOptionsExpanded\":false,\"Widgets\":{}},{\"ActivityIdRef\":\"SendHotkey_2\",\"IsAdvancedOptionsExpanded\":false,\"Widgets\":{}},{\"ActivityIdRef\":\"UiElementExists_3\",\"IsAdvancedOptionsExpanded\":false,\"Widgets\":{}},{\"ActivityIdRef\":\"Sequence_17\",\"IsAdvancedOptionsExpanded\":false,\"Widgets\":{}},{\"ActivityIdRef\":\"Assign_3\",\"IsAdvancedOptionsExpanded\":false,\"Widgets\":{}},{\"ActivityIdRef\":\"Sequence_18\",\"IsAdvancedOptionsExpanded\":false,\"Widgets\":{}},{\"ActivityIdRef\":\"Sequence_46\",\"IsAdvancedOptionsExpanded\":false,\"Widgets\":{}},{\"ActivityIdRef\":\"NTypeInto_14\",\"IsAdvancedOptionsExpanded\":false,\"Widgets\":{}},{\"ActivityIdRef\":\"Sequence_47\",\"IsAdvancedOptionsExpanded\":false,\"Widgets\":{}},{\"ActivityIdRef\":\"NTypeInto_9\",\"IsAdvancedOptionsExpanded\":false,\"Widgets\":{}},{\"ActivityIdRef\":\"NTypeInto_10\",\"IsAdvancedOptionsExpanded\":false,\"Widgets\":{}},{\"ActivityIdRef\":\"NClick_2\",\"IsAdvancedOptionsExpanded\":false,\"Widgets\":{}},{\"ActivityIdRef\":\"Sequence_44\",\"IsAdvancedOptionsExpanded\":false,\"Widgets\":{}},{\"ActivityIdRef\":\"NHover_1\",\"IsAdvancedOptionsExpanded\":false,\"Widgets\":{}},{\"ActivityIdRef\":\"NClick_16\",\"IsAdvancedOptionsExpanded\":false,\"Widgets\":{}},{\"ActivityIdRef\":\"If_12\",\"IsAdvancedOptionsExpanded\":false,\"Widgets\":{\"Then\":{\"ShowExpanded\":true},\"Else\":{\"ShowExpanded\":true}}},{\"ActivityIdRef\":\"Sequence_48\",\"IsAdvancedOptionsExpanded\":false,\"Widgets\":{}},{\"ActivityIdRef\":\"NClick_15\",\"IsAdvancedOptionsExpanded\":false,\"Widgets\":{}},{\"ActivityIdRef\":\"InvokeWorkflowFile_2\",\"IsAdvancedOptionsExpanded\":false,\"Categories\":{\"Common\":true,\"Options\":true,\"Log\":true,\"Output\":true},\"Widgets\":{}},{\"ActivityIdRef\":\"InvokeWorkflowFile_6\",\"IsAdvancedOptionsExpanded\":false,\"Categories\":{\"Common\":true,\"Options\":true,\"Log\":true,\"Output\":true},\"Widgets\":{}},{\"ActivityIdRef\":\"If_14\",\"IsAdvancedOptionsExpanded\":false,\"Widgets\":{\"Then\":{\"ShowExpanded\":true},\"Else\":{\"ShowExpanded\":true}}},{\"ActivityIdRef\":\"InvokeWorkflowFile_3\",\"IsAdvancedOptionsExpanded\":false,\"Categories\":{\"Common\":true,\"Options\":true,\"Log\":true,\"Output\":true},\"Widgets\":{}},{\"ActivityIdRef\":\"InvokeWorkflowFile_4\",\"IsAdvancedOptionsExpanded\":false,\"Categories\":{\"Common\":true,\"Options\":true,\"Log\":true,\"Output\":true},\"Widgets\":{}},{\"ActivityIdRef\":\"If_15\",\"IsAdvancedOptionsExpanded\":false,\"Widgets\":{\"Then\":{\"ShowExpanded\":true},\"Else\":{\"ShowExpanded\":true}}},{\"ActivityIdRef\":\"If_19\",\"IsAdvancedOptionsExpanded\":false,\"Widgets\":{\"Then\":{\"ShowExpanded\":true},\"Else\":{\"ShowExpanded\":true}}},{\"ActivityIdRef\":\"LogMessage_11\",\"IsAdvancedOptionsExpanded\":false,\"Widgets\":{}},{\"ActivityIdRef\":\"ExtractDocumentDataWithDocumentData`1_1\",\"IsAdvancedOptionsExpanded\":false,\"Categories\":{\"Input\":true,\"Output\":true},\"Widgets\":{}},{\"ActivityIdRef\":\"LogMessage_12\",\"IsAdvancedOptionsExpanded\":false,\"Widgets\":{}},{\"ActivityIdRef\":\"IfElseIfV2_1\",\"IsAdvancedOptionsExpanded\":false,\"Widgets\":{\"Then\":{\"ShowExpanded\":true},\"Else\":{\"ShowExpanded\":true}}},{\"ActivityIdRef\":\"Return_2\",\"IsAdvancedOptionsExpanded\":false,\"Widgets\":{}},{\"ActivityIdRef\":\"LogMessage_14\",\"IsAdvancedOptionsExpanded\":false,\"Widgets\":{}},{\"ActivityIdRef\":\"If_17\",\"IsAdvancedOptionsExpanded\":false,\"Widgets\":{\"Then\":{\"ShowExpanded\":true},\"Else\":{\"ShowExpanded\":true}}},{\"ActivityIdRef\":\"LogMessage_15\",\"IsAdvancedOptionsExpanded\":false,\"Widgets\":{}},{\"ActivityIdRef\":\"Return_3\",\"IsAdvancedOptionsExpanded\":false,\"Widgets\":{}},{\"ActivityIdRef\":\"Continue_1\",\"IsAdvancedOptionsExpanded\":false,\"Widgets\":{}},{\"ActivityIdRef\":\"If_20\",\"IsAdvancedOptionsExpanded\":false,\"Widgets\":{\"Then\":{\"ShowExpanded\":true},\"Else\":{\"ShowExpanded\":true}}},{\"ActivityIdRef\":\"LogMessage_16\",\"IsAdvancedOptionsExpanded\":false,\"Widgets\":{}},{\"ActivityIdRef\":\"IfElseIfV2_2\",\"IsAdvancedOptionsExpanded\":false,\"Widgets\":{\"Then\":{\"ShowExpanded\":true},\"Else\":{\"ShowExpanded\":true}}},{\"ActivityIdRef\":\"InvokeWorkflowFile_5\",\"IsAdvancedOptionsExpanded\":false,\"Categories\":{\"Common\":true,\"Options\":true,\"Log\":true,\"Output\":true},\"Widgets\":{}},{\"ActivityIdRef\":\"NGetText_1\",\"IsAdvancedOptionsExpanded\":false,\"Widgets\":{}},{\"ActivityIdRef\":\"Sequence_71\",\"IsAdvancedOptionsExpanded\":false,\"Widgets\":{}},{\"ActivityIdRef\":\"Sequence_72\",\"IsAdvancedOptionsExpanded\":false,\"Widgets\":{}},{\"ActivityIdRef\":\"SendHotkey_5\",\"IsAdvancedOptionsExpanded\":false,\"Widgets\":{}},{\"ActivityIdRef\":\"Comment_2\",\"IsAdvancedOptionsExpanded\":false,\"Widgets\":{}},{\"ActivityIdRef\":\"Sequence_74\",\"IsAdvancedOptionsExpanded\":false,\"Widgets\":{}},{\"ActivityIdRef\":\"IfElseIfBlock_2\",\"IsAdvancedOptionsExpanded\":false,\"Widgets\":{}},{\"ActivityIdRef\":\"Sequence_73\",\"IsAdvancedOptionsExpanded\":false,\"Widgets\":{}},{\"ActivityIdRef\":\"Sequence_75\",\"IsAdvancedOptionsExpanded\":false,\"Widgets\":{}},{\"ActivityIdRef\":\"Sequence_57\",\"IsAdvancedOptionsExpanded\":false,\"Widgets\":{}},{\"ActivityIdRef\":\"Sequence_66\",\"IsAdvancedOptionsExpanded\":false,\"Widgets\":{}},{\"ActivityIdRef\":\"Assign_10\",\"IsAdvancedOptionsExpanded\":false,\"Widgets\":{}},{\"ActivityIdRef\":\"IfElseIfBlock_1\",\"IsAdvancedOptionsExpanded\":false,\"Widgets\":{}},{\"ActivityIdRef\":\"Sequence_67\",\"IsAdvancedOptionsExpanded\":false,\"Widgets\":{}},{\"ActivityIdRef\":\"Assign_11\",\"IsAdvancedOptionsExpanded\":false,\"Widgets\":{}},{\"ActivityIdRef\":\"Sequence_68\",\"IsAdvancedOptionsExpanded\":false,\"Widgets\":{}},{\"ActivityIdRef\":\"Assign_12\",\"IsAdvancedOptionsExpanded\":false,\"Widgets\":{}},{\"ActivityIdRef\":\"Sequence_69\",\"IsAdvancedOptionsExpanded\":false,\"Widgets\":{}},{\"ActivityIdRef\":\"Sequence_70\",\"IsAdvancedOptionsExpanded\":false,\"Widgets\":{}},{\"ActivityIdRef\":\"NClick_24\",\"IsAdvancedOptionsExpanded\":false,\"Widgets\":{}},{\"ActivityIdRef\":\"NTypeInto_19\",\"IsAdvancedOptionsExpanded\":false,\"Widgets\":{}},{\"ActivityIdRef\":\"SendHotkey_3\",\"IsAdvancedOptionsExpanded\":false,\"Widgets\":{}},{\"ActivityIdRef\":\"NTypeInto_21\",\"IsAdvancedOptionsExpanded\":false,\"Widgets\":{}},{\"ActivityIdRef\":\"NClick_21\",\"IsAdvancedOptionsExpanded\":false,\"Widgets\":{}},{\"ActivityIdRef\":\"NClick_22\",\"IsAdvancedOptionsExpanded\":false,\"Widgets\":{}},{\"ActivityIdRef\":\"NTypeInto_20\",\"IsAdvancedOptionsExpanded\":false,\"Widgets\":{}},{\"ActivityIdRef\":\"SendHotkey_4\",\"IsAdvancedOptionsExpanded\":false,\"Widgets\":{}},{\"ActivityIdRef\":\"NClick_23\",\"IsAdvancedOptionsExpanded\":false,\"Widgets\":{}},{\"ActivityIdRef\":\"Sequence_58\",\"IsAdvancedOptionsExpanded\":false,\"Widgets\":{}},{\"ActivityIdRef\":\"Sequence_55\",\"IsAdvancedOptionsExpanded\":false,\"Widgets\":{}},{\"ActivityIdRef\":\"Assign_7\",\"IsAdvancedOptionsExpanded\":false,\"Widgets\":{}},{\"ActivityIdRef\":\"Sequence_56\",\"IsAdvancedOptionsExpanded\":false,\"Widgets\":{}},{\"ActivityIdRef\":\"CommentOut_2\",\"IsAdvancedOptionsExpanded\":false,\"Widgets\":{}},{\"ActivityIdRef\":\"Sequence_54\",\"IsAdvancedOptionsExpanded\":false,\"Widgets\":{}},{\"ActivityIdRef\":\"NClick_18\",\"IsAdvancedOptionsExpanded\":false,\"Widgets\":{}},{\"ActivityIdRef\":\"Sequence_49\",\"IsAdvancedOptionsExpanded\":false,\"Widgets\":{}},{\"ActivityIdRef\":\"UiElementExists_5\",\"IsAdvancedOptionsExpanded\":false,\"Widgets\":{}},{\"ActivityIdRef\":\"Sequence_50\",\"IsAdvancedOptionsExpanded\":false,\"Widgets\":{}},{\"ActivityIdRef\":\"NClick_19\",\"IsAdvancedOptionsExpanded\":false,\"Widgets\":{}},{\"ActivityIdRef\":\"Sequence_51\",\"IsAdvancedOptionsExpanded\":false,\"Widgets\":{}},{\"ActivityIdRef\":\"InvokeWorkflowFile_8\",\"IsAdvancedOptionsExpanded\":false,\"Categories\":{\"Common\":true,\"Options\":true,\"Log\":true,\"Output\":true},\"Widgets\":{}},{\"ActivityIdRef\":\"CommentOut_3\",\"IsAdvancedOptionsExpanded\":false,\"Widgets\":{}},{\"ActivityIdRef\":\"Sequence_76\",\"IsAdvancedOptionsExpanded\":false,\"Widgets\":{}},{\"ActivityIdRef\":\"ForEach`1_2\",\"IsAdvancedOptionsExpanded\":false,\"Categories\":{\"\":true},\"Widgets\":{\"Body\":{\"ShowExpanded\":true}}},{\"ActivityIdRef\":\"Assign_13\",\"IsAdvancedOptionsExpanded\":false,\"Widgets\":{}},{\"ActivityIdRef\":\"Assign_14\",\"IsAdvancedOptionsExpanded\":false,\"Widgets\":{}},{\"ActivityIdRef\":\"Assign_15\",\"IsAdvancedOptionsExpanded\":false,\"Widgets\":{}}],\"Restaurent365/ConvertLineItemFromMappings.xaml\":[{\"ActivityIdRef\":\"IfElseIfV2_1\",\"IsAdvancedOptionsExpanded\":false,\"Widgets\":{\"Then\":{\"ShowExpanded\":true},\"Else\":{\"ShowExpanded\":true}}},{\"ActivityIdRef\":\"If_1\",\"IsAdvancedOptionsExpanded\":false,\"Widgets\":{\"Then\":{\"ShowExpanded\":true},\"Else\":{\"ShowExpanded\":true}}},{\"ActivityIdRef\":\"AddDataRow_1\",\"IsAdvancedOptionsExpanded\":false,\"Widgets\":{}},{\"ActivityIdRef\":\"Sequence_1\",\"IsAdvancedOptionsExpanded\":false,\"Widgets\":{}},{\"ActivityIdRef\":\"<>c_1\",\"IsAdvancedOptionsExpanded\":false,\"Widgets\":{}},{\"ActivityIdRef\":\"BuildDataTable_1\",\"IsAdvancedOptionsExpanded\":false,\"Widgets\":{}},{\"ActivityIdRef\":\"Sequence_2\",\"IsAdvancedOptionsExpanded\":false,\"Widgets\":{}},{\"ActivityIdRef\":\"IfElseIfBlock_1\",\"IsAdvancedOptionsExpanded\":false,\"Widgets\":{}},{\"ActivityIdRef\":\"Sequence_4\",\"IsAdvancedOptionsExpanded\":false,\"Widgets\":{}},{\"ActivityIdRef\":\"ReadCsvFile_2\",\"IsAdvancedOptionsExpanded\":false,\"Widgets\":{}},{\"ActivityIdRef\":\"Assign_1\",\"IsAdvancedOptionsExpanded\":false,\"Widgets\":{}},{\"ActivityIdRef\":\"IfElseIfBlock_2\",\"IsAdvancedOptionsExpanded\":false,\"Widgets\":{}},{\"ActivityIdRef\":\"Sequence_5\",\"IsAdvancedOptionsExpanded\":false,\"Widgets\":{}},{\"ActivityIdRef\":\"ReadCsvFile_3\",\"IsAdvancedOptionsExpanded\":false,\"Widgets\":{}},{\"ActivityIdRef\":\"IfElseIfBlock_3\",\"IsAdvancedOptionsExpanded\":false,\"Widgets\":{}},{\"ActivityIdRef\":\"Sequence_9\",\"IsAdvancedOptionsExpanded\":false,\"Widgets\":{}},{\"ActivityIdRef\":\"ReadCsvFile_4\",\"IsAdvancedOptionsExpanded\":false,\"Widgets\":{}},{\"ActivityIdRef\":\"Sequence_3\",\"IsAdvancedOptionsExpanded\":false,\"Widgets\":{}},{\"ActivityIdRef\":\"ForEach`1_2\",\"IsAdvancedOptionsExpanded\":false,\"Categories\":{\"\":true},\"Widgets\":{\"Body\":{\"ShowExpanded\":true}}},{\"ActivityIdRef\":\"Assign_2\",\"IsAdvancedOptionsExpanded\":false,\"Widgets\":{}},{\"ActivityIdRef\":\"Sequence_10\",\"IsAdvancedOptionsExpanded\":false,\"Widgets\":{}},{\"ActivityIdRef\":\"Sequence_11\",\"IsAdvancedOptionsExpanded\":false,\"Widgets\":{}},{\"ActivityIdRef\":\"ExtractDocumentDataWithDocumentData`1_1\",\"IsAdvancedOptionsExpanded\":false,\"Categories\":{\"Input\":true,\"Output\":true},\"Widgets\":{}}],\"TestExtraction/TextExtractionData.xaml\":[{\"ActivityIdRef\":\"InvokeWorkflowFile_1\",\"IsAdvancedOptionsExpanded\":false,\"Categories\":{\"Common\":true,\"Options\":true,\"Log\":true,\"Output\":true},\"Widgets\":{}},{\"ActivityIdRef\":\"ExtractDocumentDataWithDocumentData`1_1\",\"IsAdvancedOptionsExpanded\":false,\"Categories\":{\"Input\":true,\"Output\":true},\"Widgets\":{}},{\"ActivityIdRef\":\"LogMessage_1\",\"IsAdvancedOptionsExpanded\":false,\"Widgets\":{}},{\"ActivityIdRef\":\"InvokeWorkflowFile_2\",\"IsAdvancedOptionsExpanded\":false,\"Categories\":{\"Common\":true,\"Options\":true,\"Log\":true,\"Output\":true},\"Widgets\":{}},{\"ActivityIdRef\":\"Sequence_1\",\"IsAdvancedOptionsExpanded\":false,\"Widgets\":{}},{\"ActivityIdRef\":\"ExtractDocumentDataWithDocumentData`1_5\",\"IsAdvancedOptionsExpanded\":false,\"Categories\":{\"Input\":true,\"Output\":true},\"Widgets\":{}},{\"ActivityIdRef\":\"<>c_1\",\"IsAdvancedOptionsExpanded\":false,\"Widgets\":{}},{\"ActivityIdRef\":\"Sequence_2\",\"IsAdvancedOptionsExpanded\":false,\"Widgets\":{}},{\"ActivityIdRef\":\"CommentOut_1\",\"IsAdvancedOptionsExpanded\":false,\"Widgets\":{}},{\"ActivityIdRef\":\"Sequence_3\",\"IsAdvancedOptionsExpanded\":false,\"Widgets\":{}},{\"ActivityIdRef\":\"NApplicationCard_1\",\"IsAdvancedOptionsExpanded\":false,\"Widgets\":{}},{\"ActivityIdRef\":\"Sequence_11\",\"IsAdvancedOptionsExpanded\":false,\"Widgets\":{}},{\"ActivityIdRef\":\"NGoToUrl_1\",\"IsAdvancedOptionsExpanded\":false,\"Widgets\":{}},{\"ActivityIdRef\":\"InterruptibleWhile_1\",\"IsAdvancedOptionsExpanded\":false,\"Categories\":{\"\":true},\"Widgets\":{}},{\"ActivityIdRef\":\"Sequence_12\",\"IsAdvancedOptionsExpanded\":false,\"Widgets\":{}},{\"ActivityIdRef\":\"Assign_1\",\"IsAdvancedOptionsExpanded\":false,\"Widgets\":{}},{\"ActivityIdRef\":\"NTypeInto_1\",\"IsAdvancedOptionsExpanded\":false,\"Widgets\":{}},{\"ActivityIdRef\":\"SendHotkey_1\",\"IsAdvancedOptionsExpanded\":false,\"Widgets\":{}},{\"ActivityIdRef\":\"NTypeInto_2\",\"IsAdvancedOptionsExpanded\":false,\"Widgets\":{}},{\"ActivityIdRef\":\"NClick_1\",\"IsAdvancedOptionsExpanded\":false,\"Widgets\":{}},{\"ActivityIdRef\":\"NClick_2\",\"IsAdvancedOptionsExpanded\":false,\"Widgets\":{}},{\"ActivityIdRef\":\"NTypeInto_3\",\"IsAdvancedOptionsExpanded\":false,\"Widgets\":{}},{\"ActivityIdRef\":\"SendHotkey_2\",\"IsAdvancedOptionsExpanded\":false,\"Widgets\":{}},{\"ActivityIdRef\":\"NClick_3\",\"IsAdvancedOptionsExpanded\":false,\"Widgets\":{}}],\"Main.xaml\":[{\"ActivityIdRef\":\"InvokeWorkflowFile_1\",\"IsAdvancedOptionsExpanded\":false,\"Categories\":{\"Common\":true,\"Options\":true,\"Log\":true},\"Widgets\":{}},{\"ActivityIdRef\":\"Sequence_1\",\"IsAdvancedOptionsExpanded\":false,\"Widgets\":{}},{\"ActivityIdRef\":\"<>c_1\",\"IsAdvancedOptionsExpanded\":false,\"Widgets\":{}}],\"Restaurent365/CalculateSLCCAccountCode.xaml\":[{\"ActivityIdRef\":\"IfElseIfV2_1\",\"IsAdvancedOptionsExpanded\":false,\"Widgets\":{\"Then\":{\"ShowExpanded\":true},\"Else\":{\"ShowExpanded\":true}}}],\"Restaurent365/Login.xaml\":[{\"ActivityIdRef\":\"GetRobotCredential_1\",\"IsAdvancedOptionsExpanded\":false,\"Categories\":{\"Misc\":true,\"Output\":true},\"Widgets\":{}},{\"ActivityIdRef\":\"If_2\",\"IsAdvancedOptionsExpanded\":false,\"Widgets\":{\"Then\":{\"ShowExpanded\":true},\"Else\":{\"ShowExpanded\":true}}}],\"Restaurent365/ConvertLineItemFromMappingsDuModel2.xaml\":[{\"ActivityIdRef\":\"AddDataRow_2\",\"IsAdvancedOptionsExpanded\":false,\"Widgets\":{}},{\"ActivityIdRef\":\"AddDataRow_1\",\"IsAdvancedOptionsExpanded\":false,\"Widgets\":{}},{\"ActivityIdRef\":\"ExtractDocumentDataWithDocumentData`1_1\",\"IsAdvancedOptionsExpanded\":false,\"Categories\":{\"Input\":true,\"Output\":true},\"Widgets\":{}},{\"ActivityIdRef\":\"Sequence_1\",\"IsAdvancedOptionsExpanded\":false,\"Widgets\":{}},{\"ActivityIdRef\":\"<>c_1\",\"IsAdvancedOptionsExpanded\":false,\"Widgets\":{}},{\"ActivityIdRef\":\"BuildDataTable_1\",\"IsAdvancedOptionsExpanded\":false,\"Widgets\":{}},{\"ActivityIdRef\":\"Sequence_12\",\"IsAdvancedOptionsExpanded\":false,\"Widgets\":{}},{\"ActivityIdRef\":\"ForEach`1_2\",\"IsAdvancedOptionsExpanded\":false,\"Categories\":{\"\":true},\"Widgets\":{\"Body\":{\"ShowExpanded\":true}}},{\"ActivityIdRef\":\"Assign_2\",\"IsAdvancedOptionsExpanded\":false,\"Widgets\":{}},{\"ActivityIdRef\":\"Sequence_10\",\"IsAdvancedOptionsExpanded\":false,\"Widgets\":{}},{\"ActivityIdRef\":\"Sequence_11\",\"IsAdvancedOptionsExpanded\":false,\"Widgets\":{}},{\"ActivityIdRef\":\"Sequence_13\",\"IsAdvancedOptionsExpanded\":false,\"Widgets\":{}},{\"ActivityIdRef\":\"IfElseIfV2_1\",\"IsAdvancedOptionsExpanded\":false,\"Widgets\":{\"Then\":{\"ShowExpanded\":true},\"Else\":{\"ShowExpanded\":true}}},{\"ActivityIdRef\":\"Comment_1\",\"IsAdvancedOptionsExpanded\":false,\"Widgets\":{}},{\"ActivityIdRef\":\"Sequence_15\",\"IsAdvancedOptionsExpanded\":false,\"Widgets\":{}},{\"ActivityIdRef\":\"ReadCsvFile_6\",\"IsAdvancedOptionsExpanded\":false,\"Widgets\":{}},{\"ActivityIdRef\":\"Assign_12\",\"IsAdvancedOptionsExpanded\":false,\"Widgets\":{}},{\"ActivityIdRef\":\"Assign_13\",\"IsAdvancedOptionsExpanded\":false,\"Widgets\":{}},{\"ActivityIdRef\":\"IfElseIfBlock_1\",\"IsAdvancedOptionsExpanded\":false,\"Widgets\":{}},{\"ActivityIdRef\":\"Sequence_14\",\"IsAdvancedOptionsExpanded\":false,\"Widgets\":{}},{\"ActivityIdRef\":\"ReadCsvFile_7\",\"IsAdvancedOptionsExpanded\":false,\"Widgets\":{}},{\"ActivityIdRef\":\"Sequence_16\",\"IsAdvancedOptionsExpanded\":false,\"Widgets\":{}},{\"ActivityIdRef\":\"Sequence_17\",\"IsAdvancedOptionsExpanded\":false,\"Widgets\":{}},{\"ActivityIdRef\":\"IfElseIfBlock_2\",\"IsAdvancedOptionsExpanded\":false,\"Widgets\":{}},{\"ActivityIdRef\":\"Sequence_19\",\"IsAdvancedOptionsExpanded\":false,\"Widgets\":{}},{\"ActivityIdRef\":\"Sequence_18\",\"IsAdvancedOptionsExpanded\":false,\"Widgets\":{}},{\"ActivityIdRef\":\"IfElseIfV2_3\",\"IsAdvancedOptionsExpanded\":false,\"Widgets\":{\"Then\":{\"ShowExpanded\":true},\"Else\":{\"ShowExpanded\":true}}}]}","ProjectSettings":"{\"IncludeSourcesByDefault\":true,\"RemoveUnusedDependencies\":false}"}